sphinx_reference_rename/__init__.py
sphinx_reference_rename-0.1.0.dist-info/METADATA
sphinx_reference_rename-0.1.0.dist-info/WHEEL
sphinx_reference_rename-0.1.0.dist-info/top_level.txt
sphinx_reference_rename-0.1.0.dist-info/RECORD
