Metadata-Version: 2.1
Name: sphinx-reference-rename
Version: 0.1.0
Summary: rename sphinx references
Home-page: https://github.com/brenns10/sphinx-reference-rename
Author: Stephen Brennan
Author-email: stephen@brennan.io
License: GPL v2
Keywords: sphinx reference rename
Platform: UNKNOWN
Classifier: License :: OSI Approved :: GNU General Public License v2 (GPLv2)
Classifier: Intended Audience :: Developers
Classifier: Framework :: Sphinx :: Extension
